pipelinenode/__init__.py
pipelinenode/commands/__init__.py
pipelinenode/commands/installer.py
pipelinenode/data/__init__.py
pipelinenode/data/data.py
pipelinenode/data/helper.py
pipelinenode/pipeline/__init__.py
pipelinenode/pipeline/node.py
pipelinenode/pipeline/pipeline.py
pipelinenode/templates/__init__.py
pipelinenode/templates/data.py
pipelinenode/templates/example_node.py
pipelinenode/templates/main.py
pipelinenode/templates/pipeline.py
pipelinenode-0.0.12.dist-info/METADATA
pipelinenode-0.0.12.dist-info/WHEEL
pipelinenode-0.0.12.dist-info/top_level.txt
pipelinenode-0.0.12.dist-info/RECORD
