Metadata-Version: 2.1
Name: pipelinenode
Version: 0.0.12
Summary: Pipeline Builder
Home-page: 
Author: Johannes Kanthak
Author-email: johannes.kanthak@kdc-solutions.de
License: MIT
Keywords: Pipeline
Classifier: Development Status :: 5 - Production/Stable
Classifier: Intended Audience :: Education
Classifier: Operating System :: Microsoft :: Windows :: Windows 10
Classifier: License :: OSI Approved :: MIT License
Classifier: Programming Language :: Python :: 3
Requires-Dist: click ==8.1.7
Requires-Dist: colorama ==0.4.6
Requires-Dist: toml ==0.10.2
Requires-Dist: pandas ==2.2.0
